scythe/__init__.py
scythe/auth/__init__.py
scythe/auth/base.py
scythe/auth/basic.py
scythe/auth/bearer.py
scythe/auth/cookie_jwt.py
scythe/behaviors/__init__.py
scythe/behaviors/base.py
scythe/behaviors/default.py
scythe/behaviors/human.py
scythe/behaviors/machine.py
scythe/behaviors/stealth.py
scythe/cli/__init__.py
scythe/cli/main.py
scythe/core/__init__.py
scythe/core/csrf.py
scythe/core/executor.py
scythe/core/headers.py
scythe/core/ttp.py
scythe/journeys/__init__.py
scythe/journeys/actions.py
scythe/journeys/base.py
scythe/journeys/executor.py
scythe/orchestrators/__init__.py
scythe/orchestrators/base.py
scythe/orchestrators/batch.py
scythe/orchestrators/distributed.py
scythe/orchestrators/scale.py
scythe/payloads/__init__.py
scythe/payloads/generators.py
scythe/ttps/__init__.py
scythe/ttps/web/__init__.py
scythe/ttps/web/csrf_validation.py
scythe/ttps/web/login_bruteforce.py
scythe/ttps/web/request_flooding.py
scythe/ttps/web/sql_injection.py
scythe/ttps/web/uuid_guessing.py
scythe_ttp-0.18.8.dist-info/licenses/LICENSE
scythe_ttp-0.18.8.dist-info/METADATA
scythe_ttp-0.18.8.dist-info/WHEEL
scythe_ttp-0.18.8.dist-info/entry_points.txt
scythe_ttp-0.18.8.dist-info/top_level.txt
scythe_ttp-0.18.8.dist-info/RECORD
