Metadata-Version: 2.4
Name: scythe-ttp
Version: 0.18.8
Summary: An extensible framework for emulating attacker TTPs with Selenium.
Author-email: EpykLab <cyber@epyklab.com>
Classifier: Programming Language :: Python :: 3
Classifier: License :: OSI Approved :: MIT License
Classifier: Operating System :: OS Independent
Classifier: Development Status :: 3 - Alpha
Classifier: Intended Audience :: Developers
Classifier: Intended Audience :: Information Technology
Classifier: Topic :: Security
Classifier: Framework :: Pytest
Requires-Python: >=3.8
License-File: LICENSE
Requires-Dist: PySocks>=1.7.1
Requires-Dist: attrs>=23.0
Requires-Dist: certifi>=2024.0
Requires-Dist: charset-normalizer>=3.0
Requires-Dist: h11>=0.14
Requires-Dist: idna>=3.0
Requires-Dist: outcome>=1.3.0
Requires-Dist: pydantic<3.0,>=2.7
Requires-Dist: requests>=2.31
Requires-Dist: selenium>=4.20
Requires-Dist: sniffio>=1.3
Requires-Dist: sortedcontainers>=2.4
Requires-Dist: trio-websocket>=0.11
Requires-Dist: trio>=0.25
Requires-Dist: typing_extensions>=4.5
Requires-Dist: urllib3<3.0,>=2.0
Requires-Dist: websocket-client>=1.8
Requires-Dist: wsproto>=1.2
Requires-Dist: typer>=0.9
Requires-Dist: shellingham>=1.5
Dynamic: license-file
